mpl_lego/__init__.py
mpl_lego/axes.py
mpl_lego/colorbar.py
mpl_lego/colors.py
mpl_lego/ellipse.py
mpl_lego/labels.py
mpl_lego/scatter.py
mpl_lego/style.py
mpl_lego-0.0.2.dist-info/LICENSE
mpl_lego-0.0.2.dist-info/METADATA
mpl_lego-0.0.2.dist-info/WHEEL
mpl_lego-0.0.2.dist-info/top_level.txt
mpl_lego-0.0.2.dist-info/RECORD
