Metadata-Version: 2.1
Name: mpl-lego
Version: 0.0.2
Summary: Extra tools and functions for matplotlib
Author-email: Pratik Sachdeva <pratik.sachdeva@berkeley.edu>
Keywords: data visualization
Classifier: Programming Language :: Python :: 3
Classifier: License :: OSI Approved :: MIT License
Classifier: Operating System :: OS Independent
Requires-Python: >=3.7
License-File: LICENSE
Requires-Dist: matplotlib
Requires-Dist: numpy
